pesapal_client/__init__.py
pesapal_client/exceptions.py
pesapal_client/utils.py
pesapal_client/v3/__init__.py
pesapal_client/v3/client.py
pesapal_client/v3/schemas.py
pesapal_client-0.1.5.dist-info/LICENSE
pesapal_client-0.1.5.dist-info/METADATA
pesapal_client-0.1.5.dist-info/WHEEL
pesapal_client-0.1.5.dist-info/RECORD
