Metadata-Version: 2.1
Name: pesapal_client
Version: 0.1.5
Summary: A Typed Python client for the Pesapal API with sync/async support, order submission, IPN management, and optional CLI tools.
Home-page: https://github.com/kiraboibrahim/pesapal-client
Author: Ibrahim Kirabo
Author-email: kiraboibra268@gmail.com
Requires-Python: >=3.9,<4.0
Classifier: Programming Language :: Python :: 3
Classifier: Programming Language :: Python :: 3.9
Classifier: Programming Language :: Python :: 3.10
Classifier: Programming Language :: Python :: 3.11
Classifier: Programming Language :: Python :: 3.12
Requires-Dist: certifi (>=2025.8.3,<2026.0.0)
Requires-Dist: httpx (>=0.28.1,<0.29.0)
Requires-Dist: pycountry (>=24.6.1,<25.0.0)
Requires-Dist: pydantic-extra-types (>=2.10.5,<3.0.0)
Requires-Dist: pydantic[email] (>=2.11.7,<3.0.0)
Project-URL: Documentation, https://kiraboibrahim.github.io/pesapal-client/
Project-URL: Repository, https://github.com/kiraboibrahim/pesapal-client
